mongobit/__init__.py
mongobit/base.py
mongobit/fields.py
mongobit/mongobit.py
mongobit/utils.py
MongoBit-2021.12.9.dist-info/METADATA
MongoBit-2021.12.9.dist-info/WHEEL
MongoBit-2021.12.9.dist-info/top_level.txt
MongoBit-2021.12.9.dist-info/RECORD
