Metadata-Version: 2.1
Name: MongoBit
Version: 2021.12.9
Summary: Simple pymongo orm
Home-page: https://github.com/lixxu/mongobit
Author: Lix Xu
Author-email: xuzenglin@gmail.com
License: BSD
Platform: any
Classifier: Environment :: Web Environment
Classifier: Intended Audience :: Developers
Classifier: License :: OSI Approved :: BSD License
Classifier: Operating System :: OS Independent
Classifier: Programming Language :: Python
Classifier: Topic :: Internet :: WWW/HTTP :: Dynamic Content
Classifier: Topic :: Software Development :: Libraries :: Python Modules
Requires-Dist: pymongo (<4.0)
Requires-Dist: six
